clspy/__init__.py
clspy/_cli_all.py
clspy/cli.py
clspy/config.py
clspy/crypto.py
clspy/db.py
clspy/log.py
clspy/pip.conf
clspy/singleton.py
clspy/utils.py
clspy/version.py
clspy-0.0.5.dist-info/AUTHORS
clspy-0.0.5.dist-info/License.py
clspy-0.0.5.dist-info/METADATA
clspy-0.0.5.dist-info/WHEEL
clspy-0.0.5.dist-info/entry_points.txt
clspy-0.0.5.dist-info/top_level.txt
clspy-0.0.5.dist-info/RECORD
